deepsig/__init__.py
deepsig/crf.py
deepsig/crfdecoding.py
deepsig/deepsig.py
deepsig/deepsigconfig.py
deepsig/helpers.py
deepsig/workenv.py
deepsig_biocomp-0.9.dist-info/LICENSE
deepsig_biocomp-0.9.dist-info/METADATA
deepsig_biocomp-0.9.dist-info/WHEEL
deepsig_biocomp-0.9.dist-info/entry_points.txt
deepsig_biocomp-0.9.dist-info/top_level.txt
deepsig_biocomp-0.9.dist-info/RECORD
