Metadata-Version: 2.1
Name: deepsig-biocomp
Version: 0.9
Summary: DeepSig - Predictor of signal peptides in proteins based on deep learning
Home-page: https://github.com/BolognaBiocomp/deepsig
Author: Castrense Savojardo
Author-email: savojard@biocomp.unibo.it
License: GPLv3
Project-URL: Bug Reports, https://github.com/BolognaBiocomp/deepsig/issues
Project-URL: Source, https://github.com/BolognaBiocomp/deepsig
Keywords: bioinformatics,annotation,bacteria,signal peptides
Platform: UNKNOWN
Classifier: Operating System :: POSIX :: Linux
Classifier: Programming Language :: Python :: 3 :: Only
Classifier: Programming Language :: Python :: 3.8
Classifier: Development Status :: 4 - Beta 
Classifier: License :: OSI Approved :: GNU General Public License v3 (GPLv3)
Classifier: Topic :: Scientific/Engineering :: Bio-Informatics
Classifier: Environment :: Console
Classifier: Intended Audience :: Science/Research
Classifier: Natural Language :: English
Requires-Python: >=3.8
Requires-Dist: biopython (>=1.78)
Requires-Dist: Keras (>=2.4.3)
Requires-Dist: tensorflow
